adafruit_sht4x.py
adafruit_circuitpython_sht4x-1.0.25.dist-info/licenses/LICENSE
adafruit_circuitpython_sht4x-1.0.25.dist-info/METADATA
adafruit_circuitpython_sht4x-1.0.25.dist-info/WHEEL
adafruit_circuitpython_sht4x-1.0.25.dist-info/top_level.txt
adafruit_circuitpython_sht4x-1.0.25.dist-info/RECORD
