Metadata-Version: 2.4
Name: adafruit-circuitpython-sht4x
Version: 1.0.25
Summary: Python library for Sensirion SHT4x temperature and humidity sensors
Author-email: Adafruit Industries <circuitpython@adafruit.com>
License: MIT
Project-URL: Homepage, https://github.com/adafruit/Adafruit_CircuitPython_SHT4x
Keywords: adafruit,blinka,circuitpython,micropython,sht4x,temperature,humidity,sensor,sht40,sensirion
Classifier: Intended Audience :: Developers
Classifier: Topic :: Software Development :: Libraries
Classifier: Topic :: Software Development :: Embedded Systems
Classifier: Topic :: System :: Hardware
Classifier: License :: OSI Approved :: MIT License
Classifier: Programming Language :: Python :: 3
License-File: LICENSE
Requires-Dist: Adafruit-Blinka
Requires-Dist: adafruit-circuitpython-busdevice
Provides-Extra: optional
Dynamic: license-file
